social_sdk_test_1_sdk/__init__.py
social_sdk_test_1_sdk/api_client.py
social_sdk_test_1_sdk/api_response.py
social_sdk_test_1_sdk/configuration.py
social_sdk_test_1_sdk/exceptions.py
social_sdk_test_1_sdk/py.typed
social_sdk_test_1_sdk/rest.py
social_sdk_test_1_sdk/api/__init__.py
social_sdk_test_1_sdk/api/brand_api.py
social_sdk_test_1_sdk/api/default_api.py
social_sdk_test_1_sdk/api/generation_api.py
social_sdk_test_1_sdk/api/healthcheck_api.py
social_sdk_test_1_sdk/api/prompt_api.py
social_sdk_test_1_sdk/api/source_api.py
social_sdk_test_1_sdk/api/swagger_api.py
social_sdk_test_1_sdk/api/swaggers_api.py
social_sdk_test_1_sdk/api/tenant_api.py
social_sdk_test_1_sdk/api/worker_api.py
social_sdk_test_1_sdk/models/__init__.py
social_sdk_test_1_sdk-0.0.1.dist-info/METADATA
social_sdk_test_1_sdk-0.0.1.dist-info/WHEEL
social_sdk_test_1_sdk-0.0.1.dist-info/top_level.txt
social_sdk_test_1_sdk-0.0.1.dist-info/RECORD
